toosimplelogging/__init__.py
toosimplelogging/core.py
toosimplelogging-0.1.0.dist-info/LICENSE
toosimplelogging-0.1.0.dist-info/METADATA
toosimplelogging-0.1.0.dist-info/WHEEL
toosimplelogging-0.1.0.dist-info/top_level.txt
toosimplelogging-0.1.0.dist-info/RECORD
