Metadata-Version: 2.2
Name: toosimplelogging
Version: 0.1.0
Summary: A lightweight logging utility with terminal color support and file output capabilities.
Home-page: https://github.com/0x6768/toosimplelogging
Author: 0x6768
Author-email: admin@yang325.eu.org
Classifier: Programming Language :: Python :: 3
Classifier: License :: OSI Approved :: MIT License
Classifier: Operating System :: OS Independent
Classifier: Topic :: Software Development :: Libraries :: Python Modules
Classifier: Topic :: System :: Logging
Requires-Python: >=3.6
License-File: LICENSE
Requires-Dist: rich
Dynamic: author
Dynamic: author-email
Dynamic: classifier
Dynamic: description
Dynamic: description-content-type
Dynamic: home-page
Dynamic: requires-dist
Dynamic: requires-python
Dynamic: summary
